{"feed": {"category": [{"term": "http://gdata.youtube.com/schemas/2007#video", "scheme": "http://schemas.google.com/g/2005#kind"}], "updated": {"$t": "2013-06-07T23:16:16.869Z"}, "xmlns$gd": "http://schemas.google.com/g/2005", "openSearch$startIndex": {"$t": 51}, "entry": [{"category": [{"term": "http://gdata.youtube.com/schemas/2007#video", "scheme": "http://schemas.google.com/g/2005#kind"}, {"term": "Education", "scheme": "http://gdata.youtube.com/schemas/2007/categories.cat", "label": "Education"}], "updated": {"$t": "2013-04-28T05:01:19.000Z"}, "gd$comments": {"gd$feedLink": {"href": "https://gdata.youtube.com/feeds/api/videos/pu6ZtzBntI8/comments", "countHint": 23, "rel": "http://gdata.youtube.com/schemas/2007#comments"}}, "title": {"$t": "Hearing, Deaf, or Hard of Hearing (hoh) which are you?", "type": "text"}, "gd$rating": {"max": 5, "average": 4.2727275, "numRaters": 22, "rel": "http://schemas.google.com/g/2005#overall", "min": 1}, "media$group": {"media$player": [{"url": "https://www.youtube.com/watch?v=pu6ZtzBntI8&feature=youtube_gdata_player"}], "media$category": [{"$t": "Education", "scheme": "http://gdata.youtube.com/schemas/2007/categories.cat", "label": "Education"}], "media$title": {"$t": "Hearing, Deaf, or Hard of Hearing (hoh) which are you?", "type": "plain"}, "yt$duration": {"seconds": "150"}, "media$content": [{"medium": "video", "url": "https://www.youtube.com/v/pu6ZtzBntI8?version=3&f=user_uploads&app=youtube_gdata", "type": "application/x-shockwave-flash", "yt$format": 5, "duration": 150, "expression": "full", "isDefault": "true"}, {"medium": "video", "url": "rtsp://v5.cache1.c.youtube.com/CigLENy73wIaHwmPtGcwt5nuphMYDSANFEgGUgx1c2VyX3VwbG9hZHMM/0/0/0/video.3gp", "type": "video/3gpp", "yt$format": 1, "duration": 150, "expression": "full"}, {"medium": "video", "url": "rtsp://v5.cache1.c.youtube.com/CigLENy73wIaHwmPtGcwt5nuphMYESARFEgGUgx1c2VyX3VwbG9hZHMM/0/0/0/video.3gp", "type": "video/3gpp", "yt$format": 6, "duration": 150, "expression": "full"}], "media$thumbnail": [{"url": "https://i.ytimg.com/vi/pu6ZtzBntI8/0.jpg", "width": 480, "time": "00:01:15", "height": 360}, {"url": "https://i.ytimg.com/vi/pu6ZtzBntI8/1.jpg", "width": 120, "time": "00:00:37.500", "height": 90}, {"url": "https://i.ytimg.com/vi/pu6ZtzBntI8/2.jpg", "width": 120, "time": "00:01:15", "height": 90}, {"url": "https://i.ytimg.com/vi/pu6ZtzBntI8/3.jpg", "width": 120, "time": "00:01:52.500", "height": 90}], "media$keywords": {}, "media$description": {"$t": "In this video I explain how when you meet a deaf person you should tell them what your hearing status is; hearing, deaf, or hard of hearing (hoh) . Watch and learn these three signs", "type": "plain"}}, "author": [{"name": {"$t": "teachmesignlanguage"}, "uri": {"$t": "https://gdata.youtube.com/feeds/api/users/teachmesignlanguage"}}], "yt$statistics": {"viewCount": "7989", "favoriteCount": "0"}, "content": {"$t": "In this video I explain how when you meet a deaf person you should tell them what your hearing status is; hearing, deaf, or hard of hearing (hoh) . Watch and learn these three signs", "type": "text"}, "link": [{"href": "https://www.youtube.com/watch?v=pu6ZtzBntI8&feature=youtube_gdata", "type": "text/html", "rel": "alternate"}, {"href": "https://gdata.youtube.com/feeds/api/videos/pu6ZtzBntI8/responses", "type": "application/atom+xml", "rel": "http://gdata.youtube.com/schemas/2007#video.responses"}, {"href": "https://gdata.youtube.com/feeds/api/videos/pu6ZtzBntI8/related", "type": "application/atom+xml", "rel": "http://gdata.youtube.com/schemas/2007#video.related"}, {"href": "https://m.youtube.com/details?v=pu6ZtzBntI8", "type": "text/html", "rel": "http://gdata.youtube.com/schemas/2007#mobile"}, {"href": "https://gdata.youtube.com/feeds/api/users/teachmesignlanguage/uploads/pu6ZtzBntI8", "type": "application/atom+xml", "rel": "self"}], "published": {"$t": "2010-11-04T01:01:39.000Z"}, "id": {"$t": "http://gdata.youtube.com/feeds/api/videos/pu6ZtzBntI8"}}, {"category": [{"term": "http://gdata.youtube.com/schemas/2007#video", "scheme": "http://schemas.google.com/g/2005#kind"}, {"term": "Education", "scheme": "http://gdata.youtube.com/schemas/2007/categories.cat", "label": "Education"}], "updated": {"$t": "2013-05-01T01:11:36.000Z"}, "gd$comments": {"gd$feedLink": {"href": "https://gdata.youtube.com/feeds/api/videos/509VzHp6Gtg/comments", "countHint": 6, "rel": "http://gdata.youtube.com/schemas/2007#comments"}}, "title": {"$t": "It's nice to meet you too!", "type": "text"}, "gd$rating": {"max": 5, "average": 4.84, "numRaters": 25, "rel": "http://schemas.google.com/g/2005#overall", "min": 1}, "media$group": {"media$player": [{"url": "https://www.youtube.com/watch?v=509VzHp6Gtg&feature=youtube_gdata_player"}], "media$category": [{"$t": "Education", "scheme": "http://gdata.youtube.com/schemas/2007/categories.cat", "label": "Education"}], "media$title": {"$t": "It's nice to meet you too!", "type": "plain"}, "yt$duration": {"seconds": "154"}, "media$content": [{"medium": "video", "url": "https://www.youtube.com/v/509VzHp6Gtg?version=3&f=user_uploads&app=youtube_gdata", "type": "application/x-shockwave-flash", "yt$format": 5, "duration": 154, "expression": "full", "isDefault": "true"}, {"medium": "video", "url": "rtsp://v5.cache2.c.youtube.com/CigLENy73wIaHwnYGnp6zFVP5xMYDSANFEgGUgx1c2VyX3VwbG9hZHMM/0/0/0/video.3gp", "type": "video/3gpp", "yt$format": 1, "duration": 154, "expression": "full"}, {"medium": "video", "url": "rtsp://v5.cache2.c.youtube.com/CigLENy73wIaHwnYGnp6zFVP5xMYESARFEgGUgx1c2VyX3VwbG9hZHMM/0/0/0/video.3gp", "type": "video/3gpp", "yt$format": 6, "duration": 154, "expression": "full"}], "media$thumbnail": [{"url": "https://i.ytimg.com/vi/509VzHp6Gtg/0.jpg", "width": 480, "time": "00:01:17", "height": 360}, {"url": "https://i.ytimg.com/vi/509VzHp6Gtg/1.jpg", "width": 120, "time": "00:00:38.500", "height": 90}, {"url": "https://i.ytimg.com/vi/509VzHp6Gtg/2.jpg", "width": 120, "time": "00:01:17", "height": 90}, {"url": "https://i.ytimg.com/vi/509VzHp6Gtg/3.jpg", "width": 120, "time": "00:01:55.500", "height": 90}], "media$keywords": {}, "media$description": {"$t": "When someone signs, \"nice to meet you\" there are typically two different ways to reply, here they are", "type": "plain"}}, "author": [{"name": {"$t": "teachmesignlanguage"}, "uri": {"$t": "https://gdata.youtube.com/feeds/api/users/teachmesignlanguage"}}], "yt$statistics": {"viewCount": "6712", "favoriteCount": "0"}, "content": {"$t": "When someone signs, \"nice to meet you\" there are typically two different ways to reply, here they are", "type": "text"}, "link": [{"href": "https://www.youtube.com/watch?v=509VzHp6Gtg&feature=youtube_gdata", "type": "text/html", "rel": "alternate"}, {"href": "https://gdata.youtube.com/feeds/api/videos/509VzHp6Gtg/responses", "type": "application/atom+xml", "rel": "http://gdata.youtube.com/schemas/2007#video.responses"}, {"href": "https://gdata.youtube.com/feeds/api/videos/509VzHp6Gtg/related", "type": "application/atom+xml", "rel": "http://gdata.youtube.com/schemas/2007#video.related"}, {"href": "https://m.youtube.com/details?v=509VzHp6Gtg", "type": "text/html", "rel": "http://gdata.youtube.com/schemas/2007#mobile"}, {"href": "https://gdata.youtube.com/feeds/api/users/teachmesignlanguage/uploads/509VzHp6Gtg", "type": "application/atom+xml", "rel": "self"}], "published": {"$t": "2010-10-26T17:25:56.000Z"}, "id": {"$t": "http://gdata.youtube.com/feeds/api/videos/509VzHp6Gtg"}}, {"category": [{"term": "http://gdata.youtube.com/schemas/2007#video", "scheme": "http://schemas.google.com/g/2005#kind"}, {"term": "Education", "scheme": "http://gdata.youtube.com/schemas/2007/categories.cat", "label": "Education"}], "updated": {"$t": "2013-06-06T23:26:04.000Z"}, "gd$comments": {"gd$feedLink": {"href": "https://gdata.youtube.com/feeds/api/videos/S40fTlJY0PQ/comments", "countHint": 20, "rel": "http://gdata.youtube.com/schemas/2007#comments"}}, "title": {"$t": "ASL Nice to meet you!", "type": "text"}, "gd$rating": {"max": 5, "average": 4.9, "numRaters": 80, "rel": "http://schemas.google.com/g/2005#overall", "min": 1}, "media$group": {"media$player": [{"url": "https://www.youtube.com/watch?v=S40fTlJY0PQ&feature=youtube_gdata_player"}], "media$category": [{"$t": "Education", "scheme": "http://gdata.youtube.com/schemas/2007/categories.cat", "label": "Education"}], "media$title": {"$t": "ASL Nice to meet you!", "type": "plain"}, "yt$duration": {"seconds": "110"}, "media$content": [{"medium": "video", "url": "https://www.youtube.com/v/S40fTlJY0PQ?version=3&f=user_uploads&app=youtube_gdata", "type": "application/x-shockwave-flash", "yt$format": 5, "duration": 110, "expression": "full", "isDefault": "true"}, {"medium": "video", "url": "rtsp://v1.cache7.c.youtube.com/CigLENy73wIaHwn00FhSTh-NSxMYDSANFEgGUgx1c2VyX3VwbG9hZHMM/0/0/0/video.3gp", "type": "video/3gpp", "yt$format": 1, "duration": 110, "expression": "full"}, {"medium": "video", "url": "rtsp://v1.cache7.c.youtube.com/CigLENy73wIaHwn00FhSTh-NSxMYESARFEgGUgx1c2VyX3VwbG9hZHMM/0/0/0/video.3gp", "type": "video/3gpp", "yt$format": 6, "duration": 110, "expression": "full"}], "media$thumbnail": [{"url": "https://i.ytimg.com/vi/S40fTlJY0PQ/0.jpg", "width": 480, "time": "00:00:55", "height": 360}, {"url": "https://i.ytimg.com/vi/S40fTlJY0PQ/1.jpg", "width": 120, "time": "00:00:27.500", "height": 90}, {"url": "https://i.ytimg.com/vi/S40fTlJY0PQ/2.jpg", "width": 120, "time": "00:00:55", "height": 90}, {"url": "https://i.ytimg.com/vi/S40fTlJY0PQ/3.jpg", "width": 120, "time": "00:01:22.500", "height": 90}], "media$keywords": {}, "media$description": {"$t": "Learn how to say nice to meet you in American Sign Language", "type": "plain"}}, "author": [{"name": {"$t": "teachmesignlanguage"}, "uri": {"$t": "https://gdata.youtube.com/feeds/api/users/teachmesignlanguage"}}], "yt$statistics": {"viewCount": "25331", "favoriteCount": "0"}, "content": {"$t": "Learn how to say nice to meet you in American Sign Language", "type": "text"}, "link": [{"href": "https://www.youtube.com/watch?v=S40fTlJY0PQ&feature=youtube_gdata", "type": "text/html", "rel": "alternate"}, {"href": "https://gdata.youtube.com/feeds/api/videos/S40fTlJY0PQ/responses", "type": "application/atom+xml", "rel": "http://gdata.youtube.com/schemas/2007#video.responses"}, {"href": "https://gdata.youtube.com/feeds/api/videos/S40fTlJY0PQ/related", "type": "application/atom+xml", "rel": "http://gdata.youtube.com/schemas/2007#video.related"}, {"href": "https://m.youtube.com/details?v=S40fTlJY0PQ", "type": "text/html", "rel": "http://gdata.youtube.com/schemas/2007#mobile"}, {"href": "https://gdata.youtube.com/feeds/api/users/teachmesignlanguage/uploads/S40fTlJY0PQ", "type": "application/atom+xml", "rel": "self"}], "published": {"$t": "2010-10-20T18:16:26.000Z"}, "id": {"$t": "http://gdata.youtube.com/feeds/api/videos/S40fTlJY0PQ"}}, {"category": [{"term": "http://gdata.youtube.com/schemas/2007#video", "scheme": "http://schemas.google.com/g/2005#kind"}, {"term": "People", "scheme": "http://gdata.youtube.com/schemas/2007/categories.cat", "label": "People & Blogs"}], "updated": {"$t": "2012-07-18T00:31:43.000Z"}, "gd$comments": {"gd$feedLink": {"href": "https://gdata.youtube.com/feeds/api/videos/l1g9XNBfAH4/comments", "countHint": 1, "rel": "http://gdata.youtube.com/schemas/2007#comments"}}, "title": {"$t": "Sign of the Week #1", "type": "text"}, "gd$rating": {"max": 5, "average": 4.6666665, "numRaters": 12, "rel": "http://schemas.google.com/g/2005#overall", "min": 1}, "media$group": {"media$player": [{"url": "https://www.youtube.com/watch?v=l1g9XNBfAH4&feature=youtube_gdata_player"}], "media$category": [{"$t": "People", "scheme": "http://gdata.youtube.com/schemas/2007/categories.cat", "label": "People & Blogs"}], "media$title": {"$t": "Sign of the Week #1", "type": "plain"}, "yt$duration": {"seconds": "101"}, "media$content": [{"medium": "video", "url": "https://www.youtube.com/v/l1g9XNBfAH4?version=3&f=user_uploads&app=youtube_gdata", "type": "application/x-shockwave-flash", "yt$format": 5, "duration": 101, "expression": "full", "isDefault": "true"}, {"medium": "video", "url": "rtsp://v7.cache5.c.youtube.com/CigLENy73wIaHwl-AF_QXD1YlxMYDSANFEgGUgx1c2VyX3VwbG9hZHMM/0/0/0/video.3gp", "type": "video/3gpp", "yt$format": 1, "duration": 101, "expression": "full"}, {"medium": "video", "url": "rtsp://v7.cache5.c.youtube.com/CigLENy73wIaHwl-AF_QXD1YlxMYESARFEgGUgx1c2VyX3VwbG9hZHMM/0/0/0/video.3gp", "type": "video/3gpp", "yt$format": 6, "duration": 101, "expression": "full"}], "media$thumbnail": [{"url": "https://i.ytimg.com/vi/l1g9XNBfAH4/0.jpg", "width": 480, "time": "00:00:50.500", "height": 360}, {"url": "https://i.ytimg.com/vi/l1g9XNBfAH4/1.jpg", "width": 120, "time": "00:00:25.250", "height": 90}, {"url": "https://i.ytimg.com/vi/l1g9XNBfAH4/2.jpg", "width": 120, "time": "00:00:50.500", "height": 90}, {"url": "https://i.ytimg.com/vi/l1g9XNBfAH4/3.jpg", "width": 120, "time": "00:01:15.750", "height": 90}], "media$keywords": {}, "media$description": {"$t": "", "type": "plain"}}, "author": [{"name": {"$t": "teachmesignlanguage"}, "uri": {"$t": "https://gdata.youtube.com/feeds/api/users/teachmesignlanguage"}}], "yt$statistics": {"viewCount": "2003", "favoriteCount": "0"}, "content": {"$t": "", "type": "text"}, "link": [{"href": "https://www.youtube.com/watch?v=l1g9XNBfAH4&feature=youtube_gdata", "type": "text/html", "rel": "alternate"}, {"href": "https://gdata.youtube.com/feeds/api/videos/l1g9XNBfAH4/responses", "type": "application/atom+xml", "rel": "http://gdata.youtube.com/schemas/2007#video.responses"}, {"href": "https://gdata.youtube.com/feeds/api/videos/l1g9XNBfAH4/related", "type": "application/atom+xml", "rel": "http://gdata.youtube.com/schemas/2007#video.related"}, {"href": "https://m.youtube.com/details?v=l1g9XNBfAH4", "type": "text/html", "rel": "http://gdata.youtube.com/schemas/2007#mobile"}, {"href": "https://gdata.youtube.com/feeds/api/users/teachmesignlanguage/uploads/l1g9XNBfAH4", "type": "application/atom+xml", "rel": "self"}], "published": {"$t": "2010-09-18T20:33:29.000Z"}, "id": {"$t": "http://gdata.youtube.com/feeds/api/videos/l1g9XNBfAH4"}}], "generator": {"$t": "YouTube data API", "version": "2.1", "uri": "http://gdata.youtube.com"}, "title": {"$t": "Uploads by teachmesignlanguage", "type": "text"}, "author": [{"name": {"$t": "teachmesignlanguage"}, "uri": {"$t": "https://gdata.youtube.com/feeds/api/users/teachmesignlanguage"}}], "xmlns$yt": "http://gdata.youtube.com/schemas/2007", "xmlns$media": "http://search.yahoo.com/mrss/", "xmlns": "http://www.w3.org/2005/Atom", "link": [{"href": "https://gdata.youtube.com/feeds/api/users/teachmesignlanguage", "type": "application/atom+xml", "rel": "related"}, {"href": "https://www.youtube.com/channel/UCMg93LeYjLd-LRtBLa6H6_g/videos", "type": "text/html", "rel": "alternate"}, {"href": "https://gdata.youtube.com/feeds/api/users/teachmesignlanguage/uploads", "type": "application/atom+xml", "rel": "http://schemas.google.com/g/2005#feed"}, {"href": "https://gdata.youtube.com/feeds/api/users/teachmesignlanguage/uploads/batch", "type": "application/atom+xml", "rel": "http://schemas.google.com/g/2005#batch"}, {"href": "https://gdata.youtube.com/feeds/api/users/teachmesignlanguage/uploads?alt=json&start-index=51&max-results=50", "type": "application/atom+xml", "rel": "self"}, {"href": "https://gdata.youtube.com/feeds/api/users/teachmesignlanguage/uploads?alt=json&start-index=1&max-results=50", "type": "application/atom+xml", "rel": "previous"}], "xmlns$openSearch": "http://a9.com/-/spec/opensearchrss/1.0/", "openSearch$itemsPerPage": {"$t": 50}, "logo": {"$t": "http://www.youtube.com/img/pic_youtubelogo_123x63.gif"}, "openSearch$totalResults": {"$t": 54}, "id": {"$t": "http://gdata.youtube.com/feeds/api/users/teachmesignlanguage/uploads"}}, "version": "1.0", "encoding": "UTF-8"}